cli.py
hnterminal/__init__.py
hnterminal/hnclient.py
hnterminal/hncontext.py
hnterminal/commands/__init__.py
hnterminal/commands/get_comments.py
hnterminal/commands/get_front_page.py
hnterminal/commands/get_story.py
hnterminal/commands/get_user.py
hnterminal/commands/login.py
hnterminal/commands/reply.py
hnterminal/commands/votes.py
hnterminal-0.7.1.dist-info/METADATA
hnterminal-0.7.1.dist-info/WHEEL
hnterminal-0.7.1.dist-info/entry_points.txt
hnterminal-0.7.1.dist-info/top_level.txt
hnterminal-0.7.1.dist-info/RECORD
