Metadata-Version: 2.2
Name: hnterminal
Version: 0.7.1
Summary: An terminal CLI env for Hacker News
Author-email: Rocky Li <aperocky@gmail.com>
License: MIT
Project-URL: Homepage, https://github.com/Aperocky/hnterminal
Project-URL: Source, https://github.com/Aperocky/hnterminal
Keywords: hacker news,cli,repl
Requires-Dist: replbuilder>=1.1.1
Requires-Dist: bs4
